pygrb_lc/__init__.py
pygrb_lc/blind_search.py
pygrb_lc/catalogs.py
pygrb_lc/config.py
pygrb_lc/crossmatching.py
pygrb_lc/fitting.py
pygrb_lc/furie.py
pygrb_lc/time.py
pygrb_lc/utils.py
pygrb_lc/light_curves/__init__.py
pygrb_lc/light_curves/light_curves.py
pygrb_lc/light_curves/transformations.py
pygrb_lc/light_curves/utils.py
pygrb_lc-0.3.7.2.dist-info/LICENSE
pygrb_lc-0.3.7.2.dist-info/METADATA
pygrb_lc-0.3.7.2.dist-info/WHEEL
pygrb_lc-0.3.7.2.dist-info/top_level.txt
pygrb_lc-0.3.7.2.dist-info/RECORD
