Metadata-Version: 2.1
Name: pygrb_lc
Version: 0.3.7.2
Summary: Python package for GRB analysis
Home-page: https://github.com/Jorezzz/pygrb_lc
Author: Mozgunov Georgiy
Author-email: georgiy99@bk.ru
Project-URL: Bug Tracker, https://github.com/Jorezzz/pygrb_lc/issues
Classifier: Programming Language :: Python :: 3
Classifier: License :: OSI Approved :: MIT License
Classifier: Operating System :: OS Independent
Requires-Python: >=3.6
License-File: LICENSE
